WIDscript/__init__.py
WIDscript-1.1.2.dist-info/LICENSE
WIDscript-1.1.2.dist-info/METADATA
WIDscript-1.1.2.dist-info/WHEEL
WIDscript-1.1.2.dist-info/top_level.txt
WIDscript-1.1.2.dist-info/RECORD
