Metadata-Version: 2.1
Name: WIDscript
Version: 1.1.2
Summary: A private wrapper made for WIDOWN releases.
Home-page: https://github.com/pypa/sampleproject
Author: WIDOWN
Author-email: widown.ma@gmail.com
Project-URL: Bug Tracker, https://github.com/pypa/sampleproject/issues
Classifier: Programming Language :: Python :: 3
Classifier: License :: OSI Approved :: MIT License
Classifier: Operating System :: OS Independent
Requires-Python: >=3.8
License-File: LICENSE
